portalcomponentscg/const.py
portalcomponentscg/exceptions.py
portalcomponentscg/logs.py
portalcomponentscg/requests_cg.py
portalcomponentscg-1.1.0.dist-info/LICENSE
portalcomponentscg-1.1.0.dist-info/METADATA
portalcomponentscg-1.1.0.dist-info/WHEEL
portalcomponentscg-1.1.0.dist-info/top_level.txt
portalcomponentscg-1.1.0.dist-info/RECORD
