Metadata-Version: 2.1
Name: portalcomponentscg
Version: 1.1.0
Summary: Components para o portal de clientes CG.
Home-page: https://github.com/ramirooliveiracg/cgcomponents
Author: Gabriel Dalacorte
Author-email: gnunes.servico@gmail.com
License: MIT
Platform: UNKNOWN
Classifier: License :: OSI Approved :: MIT License
Classifier: Programming Language :: Python :: 3
Classifier: Programming Language :: Python :: 3.7
License-File: LICENSE
Requires-Dist: requests
